setup.py
google_closure_fabric/__init__.py
google_closure_fabric/bootstrap.py
google_closure_fabric/server.py
google_closure_fabric.egg-info/PKG-INFO
google_closure_fabric.egg-info/SOURCES.txt
google_closure_fabric.egg-info/dependency_links.txt
google_closure_fabric.egg-info/top_level.txt
google_closure_fabric/base/__init__.py
google_closure_fabric/base/base_builder.py
google_closure_fabric/gjslint_ext/__init__.py
google_closure_fabric/gjslint_ext/autofix.py
google_closure_fabric/gjslint_ext/error_rules.py
google_closure_fabric/gjslint_ext/linter.py
google_closure_fabric/parts/__init__.py
google_closure_fabric/parts/deps.py
google_closure_fabric/parts/js.py
google_closure_fabric/parts/linter.py
google_closure_fabric/parts/stylesheets.py
google_closure_fabric/parts/templates.py
scripts/gclosureboilerplate