Metadata-Version: 1.1
Name: google-closure-fabric
Version: 0.0.5
Summary: fabric module for simplifying google closure integration
Home-page: https://github.com/batsuev/google-closure-fabric
Author: Aleksandr Batsuev
Author-email: batsuev@gmail.com
License: BSD
Keywords: google closure gjslint soy
Platform: UNKNOWN
Classifier: Development Status :: 1 - Planning
Classifier: Topic :: Utilities
Classifier: License :: OSI Approved :: BSD License
Requires: fabric
Requires: watchdog
